medimm/__init__.py
medimm/utils.py
medimm/layers/__init__.py
medimm/layers/layer_scale.py
medimm/layers/norm.py
medimm/losses/__init__.py
medimm/losses/dice_loss.py
medimm/models/__init__.py
medimm/models/convnext_3d.py
medimm/models/unet_3d.py
medimm/models/vit_3d.py
medimm-0.0.20.dist-info/licenses/LICENSE
medimm-0.0.20.dist-info/METADATA
medimm-0.0.20.dist-info/WHEEL
medimm-0.0.20.dist-info/top_level.txt
medimm-0.0.20.dist-info/RECORD
